{
  "type": "Feature",
  "properties": {
    "gn:gn_country":"AQ",
    "gn:gn_fcode":"STNB",
    "gn:gn_pop":5,
    "gn:population":5,
    "iso:country":"AQ",
    "name:ara_x_preferred":[
        "\u0645\u062d\u0637\u0629 \u0645\u064a\u0632\u0648\u0647\u0648"
    ],
    "name:chi_x_preferred":[
        "\u745e\u7a57\u57fa\u5730"
    ],
    "name:dut_x_preferred":[
        "Mizuho Station"
    ],
    "name:eng_x_preferred":[
        "Mizuho Station (Japan)"
    ],
    "name:eng_x_variant":[
        "Mizuho Station"
    ],
    "name:fin_x_preferred":[
        "Mizuho"
    ],
    "name:ita_x_preferred":[
        "Stazione Mizuho"
    ],
    "name:jpn_x_preferred":[
        "\u307f\u305a\u307b\u57fa\u5730"
    ],
    "name:lav_x_preferred":[
        "Midzuho"
    ],
    "name:nno_x_preferred":[
        "Mizuho-stasjonen"
    ],
    "name:nob_x_preferred":[
        "Mizuho"
    ],
    "name:nor_x_preferred":[
        "Mizuho-stasjonen (Japan)"
    ],
    "name:nor_x_variant":[
        "Mizuho"
    ],
    "name:pol_x_preferred":[
        "Mizuho"
    ],
    "name:por_x_preferred":[
        "Esta\u00e7\u00e3o Mizuho"
    ],
    "name:spa_x_preferred":[
        "Base Mizuho"
    ],
    "name:swe_x_preferred":[
        "Mizuho"
    ],
    "name:unk_x_variant":[
        "Mizuho /Nip./"
    ],
    "qs_pg:aaroncc":"AQ",
    "qs_pg:gn_country":"AQ",
    "qs_pg:gn_fcode":"STNB",
    "qs_pg:gn_pop":5,
    "qs_pg:name":"Mizuho Station",
    "qs_pg:photos_9r":0,
    "qs_pg:photos_sr":0,
    "qs_pg:pop_sr":1,
    "qs_pg:qs_pg_placetype":"locality",
    "wof:name":"Mizuho Station",
    "wof:placetype":"locality",
    "wof:population":5
},
  "geometry": {"coordinates":[44.31667,-70.68333],"type":"Point"}
}